{
    "parent": "minecraft:recipes/root",
    "rewards": {
      "recipes": [
        "lunade:glowing_green_fitting"
      ]
    },
    "criteria": {
      "has_green_fitting": {
        "trigger": "minecraft:inventory_changed",
        "conditions": {
          "items": [
            {
              "items": [
                "lunade:green_fitting"
              ]
            }
          ]
        }
      },
      "has_the_recipe": {
        "trigger": "minecraft:recipe_unlocked",
        "conditions": {
          "recipe": "lunade:glowing_green_fitting"
        }
      }
    },
    "requirements": [
      [
        "has_green_fitting",
        "has_the_recipe"
      ]
    ]
  }